tctk/AoUTools.py
tctk/HailTools.py
tctk/PolarsTools.py
tctk/__init__.py
tctk-0.1.54.dist-info/LICENSE
tctk-0.1.54.dist-info/METADATA
tctk-0.1.54.dist-info/WHEEL
tctk-0.1.54.dist-info/top_level.txt
tctk-0.1.54.dist-info/RECORD
