Metadata-Version: 2.1
Name: tctk
Version: 0.1.54
Summary: A collection of mini tools.
Home-page: https://github.com/nhgritctran/tctk
Author: Tam Tran
Author-email: tam.c.tran@outlook.com
License: GPL-3.0
License-File: LICENSE
Requires-Dist: connectorx
Requires-Dist: google-cloud-bigquery
Requires-Dist: polars
Requires-Dist: pyarrow
Requires-Dist: tableone
Requires-Dist: tqdm
